rotary_controller_python/__init__.py
rotary_controller_python/components/__init__.py
rotary_controller_python/components/appsettings.kv
rotary_controller_python/components/appsettings.py
rotary_controller_python/components/coordbar.kv
rotary_controller_python/components/coordbar.py
rotary_controller_python/components/jog.kv
rotary_controller_python/components/jog.py
rotary_controller_python/components/keypad.kv
rotary_controller_python/components/keypad.py
rotary_controller_python/components/labelbutton.kv
rotary_controller_python/components/labelbutton.py
rotary_controller_python/components/ledbutton.kv
rotary_controller_python/components/ledbutton.py
rotary_controller_python/components/servobar.kv
rotary_controller_python/components/servobar.py
rotary_controller_python/components/statusbar.kv
rotary_controller_python/components/statusbar.py
rotary_controller_python/components/synchro.kv
rotary_controller_python/components/synchro.py
rotary_controller_python/components/toolbar.kv
rotary_controller_python/components/toolbar.py
rotary_controller_python/components/viewpopup.kv
rotary_controller_python/components/viewpopup.py
rotary_controller_python/data/rotary.json
rotary_controller_python/data/units.json
rotary_controller_python/fonts/DSEG14Classic-Bold.ttf
rotary_controller_python/fonts/DSEG14Classic-BoldItalic.ttf
rotary_controller_python/fonts/DSEG14Classic-Italic.ttf
rotary_controller_python/fonts/DSEG14Classic-Light.ttf
rotary_controller_python/fonts/DSEG14Classic-LightItalic.ttf
rotary_controller_python/fonts/DSEG14Classic-Regular.ttf
rotary_controller_python/fonts/DSEG7Classic-Bold.ttf
rotary_controller_python/fonts/DSEG7Classic-BoldItalic.ttf
rotary_controller_python/fonts/DSEG7Classic-Italic.ttf
rotary_controller_python/fonts/DSEG7Classic-Light.ttf
rotary_controller_python/fonts/DSEG7Classic-LightItalic.ttf
rotary_controller_python/fonts/DSEG7Classic-Regular.ttf
rotary_controller_python/fonts/DSEG7Modern-Bold.ttf
rotary_controller_python-0.1.6.dist-info/METADATA
rotary_controller_python-0.1.6.dist-info/WHEEL
rotary_controller_python-0.1.6.dist-info/RECORD
