Metadata-Version: 2.1
Name: rotary-controller-python
Version: 0.1.6
Summary: Rotary Controller Python
License: MIT
Author: Stefano Bertelli
Author-email: bartei81@gmail.com
Requires-Python: >=3.9,<4.0
Classifier: License :: OSI Approved :: MIT License
Classifier: Programming Language :: Python :: 3
Classifier: Programming Language :: Python :: 3.9
Classifier: Programming Language :: Python :: 3.10
Classifier: Programming Language :: Python :: 3.11
Requires-Dist: cachetools (>=5.3.0,<6.0.0)
Requires-Dist: coverage (>=7.2.2,<8.0.0)
Requires-Dist: kivy (>=2.2.0,<3.0.0)
Requires-Dist: loguru (>=0.7.0,<0.8.0)
Requires-Dist: minimalmodbus (>=2.0.1,<3.0.0)
Requires-Dist: pydantic (>=1.10.6,<2.0.0)
Requires-Dist: pytest (>=7.2.2,<8.0.0)
Requires-Dist: pyyaml (>=6.0,<7.0)
